openemma/__init__.py
openemma/main.py
openemma/utils.py
openemma/llava/__init__.py
openemma/llava/constants.py
openemma/llava/conversation.py
openemma/llava/mm_utils.py
openemma/llava/mm_utils_differentiable.py
openemma/llava/utils.py
openemma/llava/model/__init__.py
openemma/llava/model/apply_delta.py
openemma/llava/model/builder.py
openemma/llava/model/consolidate.py
openemma/llava/model/llava_arch.py
openemma/llava/model/make_delta.py
openemma/llava/model/utils.py
openemma/llava/model/language_model/__init__.py
openemma/llava/model/language_model/llava_llama.py
openemma/llava/model/language_model/llava_mistral.py
openemma/llava/model/language_model/llava_mpt.py
openemma/llava/model/multimodal_encoder/__init__.py
openemma/llava/model/multimodal_encoder/builder.py
openemma/llava/model/multimodal_encoder/clip_encoder.py
openemma/llava/model/multimodal_projector/__init__.py
openemma/llava/model/multimodal_projector/builder.py
openemma/llava/serve/__init__.py
openemma/llava/serve/cli.py
openemma/llava/serve/controller.py
openemma/llava/serve/gradio_web_server.py
openemma/llava/serve/model_worker.py
openemma/llava/serve/register_worker.py
openemma/llava/serve/sglang_worker.py
openemma/llava/serve/test_message.py
openemma/llava/train/__init__.py
openemma/llava/train/llama_flash_attn_monkey_patch.py
openemma/llava/train/llama_xformers_attn_monkey_patch.py
openemma/llava/train/llava_trainer.py
openemma/llava/train/train.py
openemma/llava/train/train_mem.py
openemma/llava/train/train_xformers.py
openemma/tools/__init__.py
openemma/tools/YOLO3D/__init__.py
openemma/tools/YOLO3D/inference.py
openemma/tools/YOLO3D/main.py
openemma/tools/YOLO3D/train.py
openemma/tools/YOLO3D/library/Calib.py
openemma/tools/YOLO3D/library/Math.py
openemma/tools/YOLO3D/library/Plotting.py
openemma/tools/YOLO3D/library/__init__.py
openemma/tools/YOLO3D/models/__init__.py
openemma/tools/YOLO3D/models/common.py
openemma/tools/YOLO3D/models/experimental.py
openemma/tools/YOLO3D/models/tf.py
openemma-0.1.20.dist-info/METADATA
openemma-0.1.20.dist-info/WHEEL
openemma-0.1.20.dist-info/entry_points.txt
openemma-0.1.20.dist-info/top_level.txt
openemma-0.1.20.dist-info/RECORD
