Metadata-Version: 2.1
Name: openemma
Version: 0.1.20
Summary: OpenEMMA is an open-source implementation of Waymo's End-to-End Multimodal Model for Autonomous Driving (EMMA).
Home-page: https://github.com/taco-group/OpenEMMA
Author: Shuo Xing
Author-email: shuoxing@tamu.edu
Classifier: Development Status :: 3 - Alpha
Classifier: Intended Audience :: Developers
Classifier: License :: OSI Approved :: MIT License
Classifier: Programming Language :: Python :: 3.8
Requires-Dist: torch >=1.8.1
Requires-Dist: torchvision >=0.9.1
Requires-Dist: matplotlib >=3.2.2
Requires-Dist: numpy >=1.18.5
Requires-Dist: opencv-python >=4.1.2
Requires-Dist: Pillow >=7.1.2
Requires-Dist: PyYAML >=5.3.1
Requires-Dist: requests >=2.23.0
Requires-Dist: scipy >=1.4.1
Requires-Dist: tqdm >=4.41.0
Requires-Dist: gdown
Requires-Dist: flask
Requires-Dist: Werkzeug
Requires-Dist: argparse
Requires-Dist: transformers >=4.46.2
Requires-Dist: ultralytics
Requires-Dist: qwen-vl-utils
Requires-Dist: pyquaternion
Requires-Dist: nuscenes-devkit
Requires-Dist: openai
Requires-Dist: pandas >=1.1.4
Requires-Dist: seaborn >=0.11.0
Requires-Dist: thop
Requires-Dist: accelerate >=0.26.0
